ScikitLearnGuanfangWendangShili/README.md
ScikitLearnGuanfangWendangShili/__init__.py
ScikitLearnGuanfangWendangShili/__main__.py
ScikitLearnGuanfangWendangShili/file.epub
ScikitLearnGuanfangWendangShili/index.html
ScikitLearnGuanfangWendangShili/css/__init__.py
ScikitLearnGuanfangWendangShili/css/annotations.css
ScikitLearnGuanfangWendangShili/css/main.css
ScikitLearnGuanfangWendangShili/css/normalize.css
ScikitLearnGuanfangWendangShili/css/popup.css
ScikitLearnGuanfangWendangShili/font/__init__.py
ScikitLearnGuanfangWendangShili/font/fontello.eot
ScikitLearnGuanfangWendangShili/font/fontello.svg
ScikitLearnGuanfangWendangShili/font/fontello.ttf
ScikitLearnGuanfangWendangShili/font/fontello.woff
ScikitLearnGuanfangWendangShili/img/__init__.py
ScikitLearnGuanfangWendangShili/img/annotator-glyph-sprite.png
ScikitLearnGuanfangWendangShili/img/annotator-icon-sprite.png
ScikitLearnGuanfangWendangShili/img/apple-touch-icon.png
ScikitLearnGuanfangWendangShili/img/cancelfullscreen.png
ScikitLearnGuanfangWendangShili/img/close.png
ScikitLearnGuanfangWendangShili/img/fullscreen.png
ScikitLearnGuanfangWendangShili/img/loader.gif
ScikitLearnGuanfangWendangShili/img/menu-icon.png
ScikitLearnGuanfangWendangShili/img/save.png
ScikitLearnGuanfangWendangShili/img/saved.png
ScikitLearnGuanfangWendangShili/img/settings-s.png
ScikitLearnGuanfangWendangShili/img/settings.png
ScikitLearnGuanfangWendangShili/img/star.png
ScikitLearnGuanfangWendangShili/js/__init__.py
ScikitLearnGuanfangWendangShili/js/epub.js
ScikitLearnGuanfangWendangShili/js/epub.min.js
ScikitLearnGuanfangWendangShili/js/epub.min.map
ScikitLearnGuanfangWendangShili/js/hooks.min.js
ScikitLearnGuanfangWendangShili/js/hooks.min.map
ScikitLearnGuanfangWendangShili/js/reader.js
ScikitLearnGuanfangWendangShili/js/reader.js.map
ScikitLearnGuanfangWendangShili/js/reader.min.js
ScikitLearnGuanfangWendangShili/js/reader.min.map
ScikitLearnGuanfangWendangShili/js/hooks/__init__.py
scikit_learn_guanfang_wendang_shili-2024.3.2.0.dist-info/METADATA
scikit_learn_guanfang_wendang_shili-2024.3.2.0.dist-info/WHEEL
scikit_learn_guanfang_wendang_shili-2024.3.2.0.dist-info/entry_points.txt
scikit_learn_guanfang_wendang_shili-2024.3.2.0.dist-info/top_level.txt
scikit_learn_guanfang_wendang_shili-2024.3.2.0.dist-info/RECORD
